facebooklogger/__init__.py
facebooklogger/__main__.py
facebooklogger/_version.py
facebooklogger/getuserid.py
facebooklogger/logger.py
facebooklogger/settings.py
facebooklogger-0.2.4.dist-info/LICENSE
facebooklogger-0.2.4.dist-info/METADATA
facebooklogger-0.2.4.dist-info/WHEEL
facebooklogger-0.2.4.dist-info/top_level.txt
facebooklogger-0.2.4.dist-info/RECORD
