Metadata-Version: 2.1
Name: facebooklogger
Version: 0.2.4
Summary: A logging handler that sends you log entries on Facebook Messenger
Home-page: https://github.com/jackadamson/facebooklogger
Author: Jack Adamson
Author-email: jack@mrfluffybunny.com
License: UNKNOWN
Platform: UNKNOWN
Classifier: Programming Language :: Python :: 3
Classifier: License :: OSI Approved :: MIT License
Classifier: Topic :: System :: Logging
Classifier: Topic :: System :: Monitoring
Classifier: Intended Audience :: Developers
Classifier: Intended Audience :: System Administrators
Classifier: Development Status :: 4 - Beta
Requires-Python: >=3.6
Requires-Dist: pymessenger
Requires-Dist: environs
Requires-Dist: requests
